tesstractor/IDA-SQM-template.tpl
tesstractor/IDA-TESS-template.tpl
tesstractor/__init__.py
tesstractor/base.ini
tesstractor/cli.py
tesstractor/device.py
tesstractor/mqtt.py
tesstractor/plot.py
tesstractor/reader.py
tesstractor/sqm.py
tesstractor/tess.py
tesstractor/workers.py
tesstractor/writef.py
tesstractor/tests/__init__.py
tesstractor/tests/test_cli.py
tesstractor/tests/test_nsbm.py
tesstractor/tests/test_sqm.py
tesstractor-0.7.0.dist-info/LICENSE.txt
tesstractor-0.7.0.dist-info/METADATA
tesstractor-0.7.0.dist-info/WHEEL
tesstractor-0.7.0.dist-info/entry_points.txt
tesstractor-0.7.0.dist-info/top_level.txt
tesstractor-0.7.0.dist-info/RECORD
