Metadata-Version: 2.1
Name: tesstractor
Version: 0.7.0
Summary: TESS photometer reading software
Author-email: Sergio Pascual <sergiopr@fis.ucm.es>
License: GPL-3.0-or-later
Project-URL: Homepage, https://github.com/guaix-ucm/tesstractor
Project-URL: Repository, https://github.com/guaix-ucm/tesstractor.git
Classifier: Programming Language :: Python :: 3.8
Classifier: Programming Language :: Python :: 3.9
Classifier: Programming Language :: Python :: 3.10
Classifier: Programming Language :: Python :: 3.11
Classifier: Programming Language :: Python :: 3.12
Classifier: Development Status :: 3 - Alpha
Classifier: Environment :: Console
Classifier: Intended Audience :: Science/Research
Classifier: License :: OSI Approved :: GNU General Public License (GPL)
Classifier: Operating System :: OS Independent
Classifier: Topic :: Scientific/Engineering :: Astronomy
Requires-Python: >=3.8
License-File: LICENSE.txt
Requires-Dist: pytz
Requires-Dist: tzlocal
Requires-Dist: pyserial
Requires-Dist: paho-mqtt
Requires-Dist: attrs >=17.4.0
Requires-Dist: matplotlib
Requires-Dist: numpy
Requires-Dist: astroplan
Requires-Dist: astropy
Provides-Extra: docs
Requires-Dist: sphinx ; extra == 'docs'
Provides-Extra: test
Requires-Dist: pytest ; extra == 'test'
